pyola/__init__.py
pyola/input.py
pyola/renderer.py
pyola/shapes.py
pyola/text.py
pyola/window.py
pyola-0.2.0.dist-info/licenses/LICENSE
pyola-0.2.0.dist-info/METADATA
pyola-0.2.0.dist-info/WHEEL
pyola-0.2.0.dist-info/top_level.txt
pyola-0.2.0.dist-info/RECORD
